gae_returns/__init__.py
gae_returns/returns.py
sannidhi_gae_returns_20251112-0.0.1.dist-info/METADATA
sannidhi_gae_returns_20251112-0.0.1.dist-info/WHEEL
sannidhi_gae_returns_20251112-0.0.1.dist-info/licenses/LICENSE
sannidhi_gae_returns_20251112-0.0.1.dist-info/RECORD
