Metadata-Version: 2.4
Name: sannidhi-gae-returns-20251112
Version: 0.0.1
Summary: Discounted returns utilities for Reinforcement Learning: discounted cumulative sums, n-step TD targets, and Generalized Advantage Estimation (GAE). Created by Sannidhi Nair for B.Tech AI (RL Practicum, NMIMS MPSTME).
Project-URL: Homepage, https://pypi.org/project/sannidhi-gae-returns-20251112/
Project-URL: Repository, https://github.com/SannidhiNair/sannidhi-gae-returns-20251112
Author-email: Sannidhi Nair <sannidhi.nair88@nmims.in>
License: MIT
License-File: LICENSE
Keywords: advantages,gae,n-step,reinforcement-learning,returns,rl,sannidhi-nair
Classifier: Development Status :: 4 - Beta
Classifier: Intended Audience :: Education
Classifier: License :: OSI Approved :: MIT License
Classifier: Operating System :: OS Independent
Classifier: Programming Language :: Python :: 3
Classifier: Topic :: Scientific/Engineering :: Artificial Intelligence
Requires-Python: >=3.8
